{
"type": "FeatureCollection",
"name": "Pemerintahan",
"crs": { "type": "name", "properties": { "name": "urn:ogc:def:crs:OGC:1.3:CRS84" } },
"features": [
{ "type": "Feature", "properties": { "NAMOBJ": "Kantor Desa Rejoagung", "FGSGOV": null, "LUAS": null, "FCODE": null, "REMARK": null, "SRS_ID": null, "LCODE": null, "METADATA": null }, "geometry": { "type": "Point", "coordinates": [ 114.308688891876855, -8.379341706680984, 0.0 ] } }
]
}
